sumiTest/test1.py
sumiTest/test2.py
sumiTest-0.0.0.2.dist-info/METADATA
sumiTest-0.0.0.2.dist-info/WHEEL
sumiTest-0.0.0.2.dist-info/top_level.txt
sumiTest-0.0.0.2.dist-info/RECORD
