Metadata-Version: 2.1
Name: sumiTest
Version: 0.0.0.2
Summary: My First Test Package
Home-page: https://lingua.blog.me/…
Author: Sumi Park
Author-email: psunni@naver.com
License: MIT
Requires-Python: >=3
